shayblaexample.py
shayblaexample-1.0.1.dist-info/DESCRIPTION.rst
shayblaexample-1.0.1.dist-info/METADATA
shayblaexample-1.0.1.dist-info/RECORD
shayblaexample-1.0.1.dist-info/WHEEL
shayblaexample-1.0.1.dist-info/metadata.json
shayblaexample-1.0.1.dist-info/top_level.txt
