Metadata-Version: 2.0
Name: shayblaexample
Version: 1.0.1
Summary: A simple printer of nested lists by shaybla
Home-page: http://weibo.com/u/2703925041/home?wvr=5
Author: Shay
Author-email: shay_bla@126.com
License: UNKNOWN
Platform: UNKNOWN
